aagora/__init__.py
aagora/core.py
aagora/agents/__init__.py
aagora/agents/api_agents.py
aagora/agents/base.py
aagora/agents/cli_agents.py
aagora/cli/__init__.py
aagora/cli/main.py
aagora/debate/__init__.py
aagora/debate/orchestrator.py
aagora/evolution/__init__.py
aagora/evolution/evolver.py
aagora/memory/__init__.py
aagora/memory/embeddings.py
aagora/memory/store.py
aagora-0.4.0.dist-info/METADATA
aagora-0.4.0.dist-info/WHEEL
aagora-0.4.0.dist-info/entry_points.txt
aagora-0.4.0.dist-info/top_level.txt
aagora-0.4.0.dist-info/RECORD
