Metadata-Version: 2.4
Name: aagora
Version: 0.4.0
Summary: Multi-Agent Debate Framework - A society of AI agents that discuss, critique, and improve each other's responses
Author: Agora Contributors
License: MIT
Project-URL: Homepage, https://aagora.ai
Project-URL: Documentation, https://github.com/an0mium/aagora#readme
Project-URL: Repository, https://github.com/an0mium/aagora
Project-URL: Issues, https://github.com/an0mium/aagora/issues
Keywords: ai,multi-agent,debate,llm,claude,gpt,consensus,self-improvement
Classifier: Development Status :: 3 - Alpha
Classifier: Intended Audience :: Developers
Classifier: Intended Audience :: Science/Research
Classifier: License :: OSI Approved :: MIT License
Classifier: Programming Language :: Python :: 3
Classifier: Programming Language :: Python :: 3.10
Classifier: Programming Language :: Python :: 3.11
Classifier: Programming Language :: Python :: 3.12
Classifier: Topic :: Scientific/Engineering :: Artificial Intelligence
Requires-Python: >=3.10
Requires-Dist: aiohttp>=3.9
Provides-Extra: dev
Requires-Dist: pytest>=7.0; extra == "dev"
Requires-Dist: pytest-asyncio>=0.21; extra == "dev"
Requires-Dist: black>=23.0; extra == "dev"
Requires-Dist: ruff>=0.1; extra == "dev"
